{
  "Lixue": {
    "参访里程": {
      "source": [
        [
          "month",
          "distance"
        ],
        [
          "1",
          10
        ],
        [
          "2",
          20
        ],
        [
          "3",
          40
        ],
        [
          "4",
          60
        ],
        [
          "5",
          80
        ],
        [
          "6",
          100
        ],
        [
          "7",
          120
        ],
        [
          "8",
          140
        ],
        [
          "9",
          160
        ],
        [
          "10",
          180
        ],
        [
          "11",
          200
        ],
        [
          "12",
          220
        ]
      ]
    },
    "参与人数": {
      "source": [
        [
          "category",
          "value"
        ],
        [
          "总人数",
          100
        ],
        [
          "男生",
          80
        ],
        [
          "女生",
          20
        ]
      ],
      "content": 88888
    },
    "年级专业人数": {
      "_comment": "其中abcd代表专业,按照格式往下扩展,source对应的2021是年份,后面跟着abcd对应的人数",
      "dimensions": [
        "xAxis",
        "A",
        "B",
        "C",
        "D"
      ],
      "source": [
        [
          "2021",
          20,
          40,
          60,
          80
        ],
        [
          "2022",
          10,
          30,
          50,
          70
        ],
        [
          "2023",
          10,
          20,
          30,
          40
        ],
        [
          "2024",
          20,
          50,
          70,
          90
        ]
      ]
    },
    "毕业去向": {
      "status": "success",
      "data": [
        {
          "name": "考研",
          "value": 176
        },
        {
          "name": "就业",
          "value": 288
        },
        {
          "name": "留学",
          "value": 85
        }, 
        {
          "_comment":"以下两条有就写,没有的话上面2条就够用了",
          "name": "其他",
          "value": 55
        }
      ]
    }
  },

  "DingHaiyang":{
    "CompanyLog":{
      "code":"1",
      "msg":"操作成功",
      "result":[
        {"id":1,"name":"百度","url":"/src/assets/images/baidu.png"},
        {"id":2,"name":"阿里","url":"/src/assets/images/ali.png"},
        {"id":3,"name":"xx","url":"/src/assets/images/xx.png"}
      ]
    },

    "VisitCompanyList":{
      "code":"1",
      "msg":"操作成功",
      "result":[
        {"id":1,"name":"百度","PeopleNum":20,"date":"xxxx年xx月xx日","url":"xxxxxxxxxxx"},
        {"id":2,"name":"阿里","PeopleNum":40,"date":"xxxx年xx月xx日","url":"xxxxxxxxxxx"},
        {"id":3,"name":"xx","PeopleNum":100,"date":"xxxx年xx月xx日","url":"xxxxxxxxxxx"}
      ]
    },
    "StudentList":{
      "code":"1",
      "msg":"操作成功",
      "result":[
        {"id":1,"name":"张三","sex":"男","grade":"20xx级","profession":"人工智能","VisitCompany":"阿里","credits":10},
        {"id":2,"name":"李四","sex":"女","grade":"20xx级","profession":"智能科学与技术","VisitCompany":"百度","credits":5},
        {"id":3,"name":"xx","sex":"男","grade":"20xx级","profession":"xxxxxxx","VisitCompany":"xx","credits":3}
      ]
    }
  }
}